LICENSE
README.md
setup.py
factorgraph/__init__.py
factorgraph/factorgraph.py
factorgraph.egg-info/PKG-INFO
factorgraph.egg-info/SOURCES.txt
factorgraph.egg-info/dependency_links.txt
factorgraph.egg-info/requires.txt
factorgraph.egg-info/top_level.txt